README.rst
setup.cfg
setup.py
amorphous/__init__.py
amorphous/admin.py
amorphous/apps.py
amorphous/forms.py
amorphous/views.py
amorphous/tests/__init__.py
amorphous/tests/apps.py
amorphous/tests/models.py
amorphous/tests/tests.py
django_amorphous.egg-info/PKG-INFO
django_amorphous.egg-info/SOURCES.txt
django_amorphous.egg-info/dependency_links.txt
django_amorphous.egg-info/not-zip-safe
django_amorphous.egg-info/requires.txt
django_amorphous.egg-info/top_level.txt