Metadata-Version: 1.1
Name: django-amorphous
Version: 0.4
Summary: django-amorphous unlocks the power of JsonField
Home-page: https://github.com/japrogramer/django-amorphous
Author: Jorge Perez
Author-email: japrogramer@gmail.com
License: BSD
Keywords: django,json,JsonField,amorphous
Platform: UNKNOWN
Classifier: Development Status :: 3 - Alpha
Classifier: Environment :: Web Environment
Classifier: Intended Audience :: Developers
Classifier: License :: OSI Approved :: BSD License
Classifier: Operating System :: OS Independent
Classifier: Programming Language :: Python
Classifier: Framework :: Django
